aiowhitebit/__init__.py
aiowhitebit/config.py
aiowhitebit/constants.py
aiowhitebit/exceptions.py
aiowhitebit/clients/__init__.py
aiowhitebit/clients/base.py
aiowhitebit/clients/private/__init__.py
aiowhitebit/clients/private/v4.py
aiowhitebit/clients/public/__init__.py
aiowhitebit/clients/public/v1.py
aiowhitebit/clients/public/v2.py
aiowhitebit/clients/public/v4.py
aiowhitebit/clients/webhook/__init__.py
aiowhitebit/clients/webhook/webhook_client.py
aiowhitebit/clients/websocket/__init__.py
aiowhitebit/clients/websocket/public.py
aiowhitebit/clients/websocket/subscriber.py
aiowhitebit/converters/__init__.py
aiowhitebit/converters/private/__init__.py
aiowhitebit/converters/private/v4.py
aiowhitebit/converters/public/__init__.py
aiowhitebit/converters/public/v1.py
aiowhitebit/converters/public/v2.py
aiowhitebit/converters/public/v4.py
aiowhitebit/models/__init__.py
aiowhitebit/models/base.py
aiowhitebit/models/private/__init__.py
aiowhitebit/models/private/request.py
aiowhitebit/models/private/response.py
aiowhitebit/models/public/__init__.py
aiowhitebit/models/public/v1/__init__.py
aiowhitebit/models/public/v1/request.py
aiowhitebit/models/public/v1/response.py
aiowhitebit/models/public/v2/__init__.py
aiowhitebit/models/public/v2/request.py
aiowhitebit/models/public/v2/response.py
aiowhitebit/models/public/v4/__init__.py
aiowhitebit/models/public/v4/request.py
aiowhitebit/models/public/v4/response.py
aiowhitebit/models/webhook/__init__.py
aiowhitebit/models/webhook/payload.py
aiowhitebit/models/websocket/__init__.py
aiowhitebit/models/websocket/bookticker.py
aiowhitebit/models/websocket/depth.py
aiowhitebit/models/websocket/request.py
aiowhitebit/models/websocket/response.py
aiowhitebit/utils/rate_limiting.py
aiowhitebit/utils/validation.py
aiowhitebit-0.4.0.dist-info/METADATA
aiowhitebit-0.4.0.dist-info/WHEEL
aiowhitebit-0.4.0.dist-info/licenses/LICENSE
aiowhitebit-0.4.0.dist-info/RECORD
