Metadata-Version: 2.4
Name: aiowhitebit
Version: 0.4.0
Summary: Async Python client for WhiteBit API
Project-URL: Homepage, https://github.com/doubeldare704/aiowhitebit
Project-URL: Documentation, https://github.com/doubeldare704/aiowhitebit#readme
Project-URL: Repository, https://github.com/doubeldare704/aiowhitebit.git
Project-URL: Issues, https://github.com/doubeldare704/aiowhitebit/issues
Author-email: Oleksii Ovdiienko <doubledare704@gmail.com>
License: MIT
License-File: LICENSE
Keywords: api,async,crypto,exchange,trading,whitebit
Classifier: Development Status :: 4 - Beta
Classifier: Framework :: AsyncIO
Classifier: Intended Audience :: Developers
Classifier: License :: OSI Approved :: MIT License
Classifier: Programming Language :: Python :: 3
Classifier: Programming Language :: Python :: 3.10
Classifier: Programming Language :: Python :: 3.11
Classifier: Programming Language :: Python :: 3.12
Classifier: Topic :: Software Development :: Libraries :: Python Modules
Requires-Python: >=3.10
Requires-Dist: aiodns==3.5.0
Requires-Dist: aiohttp==3.13.1
Requires-Dist: pydantic==2.12.3
Requires-Dist: uvloop==0.22.1
Requires-Dist: websocket-client==1.9.0
Requires-Dist: websockets==15.0.1
